algo_trade_v1/__init__.py
algo_trade_v1/libs/__init__.py
algo_trade_v1/libs/data_fetcher.py
algo_trade_v1/libs/fundamental_analyzer.py
algo_trade_v1/libs/pump_ranking_analyzer.py
algo_trade_v1/libs/signal_analyzer.py
algo_trade_v1/libs/technical_analyzer.py
algo_trade_v1/libs/volume_profile_analyzer.py
algo_trade_v1-0.1.0.dist-info/licenses/LICENSE
algo_trade_v1-0.1.0.dist-info/METADATA
algo_trade_v1-0.1.0.dist-info/WHEEL
algo_trade_v1-0.1.0.dist-info/top_level.txt
algo_trade_v1-0.1.0.dist-info/RECORD
